{
  "execution_info": {
    "timestamp": "2025-09-18T22:33:13.376461",
    "date": "2025-09-18",
    "time": "22:33:13",
    "config_file": "config.json",
    "dataset_file": "coffee_shop_revenue.csv"
  },
  "system_info": {
    "platform": "Windows-11-10.0.26100-SP0",
    "python_version": "3.13.4 (tags/v3.13.4:8a526ec, Jun  3 2025, 17:46:04) [MSC v.1943 64 bit (AMD64)]",
    "architecture": "64bit",
    "processor": "Intel64 Family 6 Model 126 Stepping 5, GenuineIntel",
    "machine": "AMD64"
  },
  "package_versions": {
    "pandas": "2.3.2",
    "numpy": "2.3.3",
    "matplotlib": "3.10.6",
    "seaborn": "0.13.2",
    "scikit-learn": "1.7.2",
    "joblib": "1.5.2"
  },
  "configuration": {
    "data": {
      "csv_path": "coffee_shop_revenue.csv",
      "target_column": "Daily_Revenue"
    },
    "preprocessing": {
      "test_size": 0.2,
      "random_state": 42,
      "scaler_type": "StandardScaler"
    },
    "models": {
      "linear_regression": {
        "enabled": true,
        "hyperparameters": {
          "fit_intercept": true,
          "normalize": false
        }
      },
      "svm": {
        "enabled": true,
        "hyperparameters": {
          "C": [
            0.1,
            1,
            10,
            100
          ],
          "gamma": [
            "scale",
            "auto",
            0.001,
            0.01,
            0.1,
            1
          ],
          "kernel": [
            "rbf",
            "linear",
            "poly"
          ]
        }
      },
      "decision_tree": {
        "enabled": true,
        "hyperparameters": {
          "max_depth": [
            3,
            5,
            10,
            15,
            20
          ],
          "min_samples_split": [
            2,
            5,
            10,
            20
          ],
          "min_samples_leaf": [
            1,
            2,
            4,
            8
          ]
        }
      },
      "random_forest": {
        "enabled": true,
        "hyperparameters": {
          "n_estimators": [
            50,
            100,
            200,
            300
          ],
          "max_depth": [
            3,
            5,
            10,
            15
          ],
          "min_samples_split": [
            2,
            5,
            10
          ],
          "min_samples_leaf": [
            1,
            2,
            4
          ]
        }
      },
      "neural_network": {
        "enabled": true,
        "hyperparameters": {
          "hidden_layer_sizes": [
            [
              50
            ],
            [
              100
            ],
            [
              50,
              50
            ],
            [
              100,
              50
            ]
          ],
          "activation": [
            "relu",
            "tanh"
          ],
          "solver": [
            "adam",
            "lbfgs"
          ],
          "alpha": [
            0.0001,
            0.001,
            0.01
          ]
        }
      }
    },
    "training": {
      "cv_folds": 5,
      "n_iter": 50,
      "scoring": "neg_mean_squared_error",
      "n_jobs": -1,
      "random_state": 42
    },
    "output": {
      "reports_dir": "reports",
      "tables_dir": "reports/tables",
      "figures_dir": "reports/figures",
      "models_dir": "models_store",
      "save_models": true,
      "save_scaler": true,
      "save_predictions": true,
      "save_comparison": true
    },
    "eda": {
      "generate_plots": true,
      "save_plots": true,
      "plot_types": [
        "distributions",
        "correlations",
        "scatter_pairs"
      ]
    }
  },
  "dataset_info": {
    "file_path": "coffee_shop_revenue.csv",
    "file_size_bytes": 66475,
    "sha256_hash": "65cbae03b79e3896c6a61e4cc76b228d7468a8f2169182d34d4f6c9e93b58a2b",
    "last_modified": "2025-02-07T07:29:18"
  },
  "reproducibility": {
    "numpy_random_seed": "Fijo en configuración",
    "python_random_seed": "Fijo en configuración",
    "sklearn_random_state": 42,
    "note": "Todos los random_state están fijados para reproducibilidad"
  }
}